conman/__init__.py
conman/redirects/__init__.py
conman/redirects/admin.py
conman/redirects/models.py
conman/redirects/views.py
conman/redirects/migrations/0001_initial.py
conman/redirects/migrations/0002_urlredirect.py
conman/redirects/migrations/0003_add_verbose_names_and_help_text.py
conman/redirects/migrations/__init__.py
conman/routes/__init__.py
conman/routes/admin.py
conman/routes/apps.py
conman/routes/checks.py
conman/routes/exceptions.py
conman/routes/handlers.py
conman/routes/managers.py
conman/routes/models.py
conman/routes/urls.py
conman/routes/utils.py
conman/routes/validators.py
conman/routes/views.py
conman/routes/migrations/0001_initial.py
conman/routes/migrations/0002_remove_slug_parent.py
conman/routes/migrations/0003_add_validators.py
conman/routes/migrations/__init__.py
django_conman-0.1.1.dist-info/DESCRIPTION.rst
django_conman-0.1.1.dist-info/METADATA
django_conman-0.1.1.dist-info/RECORD
django_conman-0.1.1.dist-info/WHEEL
django_conman-0.1.1.dist-info/metadata.json
django_conman-0.1.1.dist-info/top_level.txt
