Metadata-Version: 2.0
Name: django-conman
Version: 0.1.1
Summary: A lightweight CMS for django
Home-page: https://github.com/meshy/django-conman/
Author: Charlie Denton
Author-email: charlie@meshy.co.uk
License: UNKNOWN
Platform: UNKNOWN
Classifier: Development Status :: 1 - Planning
Classifier: Framework :: Django
Classifier: Intended Audience :: Developers
Classifier: License :: OSI Approved :: BSD License
Classifier: Natural Language :: English
Classifier: Programming Language :: Python :: 3 :: Only
Classifier: Programming Language :: Python :: 3
Classifier: Programming Language :: Python :: 3.4
Classifier: Programming Language :: Python :: 3.5
Classifier: Programming Language :: Python :: 3.6
Classifier: Topic :: Internet :: WWW/HTTP :: Dynamic Content
Requires-Dist: django-polymorphic (~=1.2.0)
